{
  "id": "f4d7c5ae-094d-43dc-bfbe-308f3028a7ab",
  "prevId": "8794e9ef-8f9d-4234-8103-d1836cfa8e1c",
  "version": "7",
  "dialect": "postgresql",
  "tables": {
    "public.brands": {
      "name": "brands",
      "schema": "",
      "columns": {
        "id": {
          "name": "id",
          "type": "uuid",
          "primaryKey": true,
          "notNull": true,
          "default": "uuidv7()"
        },
        "name": {
          "name": "name",
          "type": "varchar(255)",
          "primaryKey": false,
          "notNull": true
        },
        "icon": {
          "name": "icon",
          "type": "varchar(255)",
          "primaryKey": false,
          "notNull": false
        }
      },
      "indexes": {},
      "foreignKeys": {},
      "compositePrimaryKeys": {},
      "uniqueConstraints": {},
      "policies": {},
      "checkConstraints": {},
      "isRLSEnabled": false
    },
    "public.categories": {
      "name": "categories",
      "schema": "",
      "columns": {
        "id": {
          "name": "id",
          "type": "uuid",
          "primaryKey": true,
          "notNull": true,
          "default": "uuidv7()"
        },
        "name": {
          "name": "name",
          "type": "varchar(255)",
          "primaryKey": false,
          "notNull": true
        }
      },
      "indexes": {},
      "foreignKeys": {},
      "compositePrimaryKeys": {},
      "uniqueConstraints": {},
      "policies": {},
      "checkConstraints": {},
      "isRLSEnabled": false
    },
    "public.datasheets": {
      "name": "datasheets",
      "schema": "",
      "columns": {
        "id": {
          "name": "id",
          "type": "uuid",
          "primaryKey": true,
          "notNull": true,
          "default": "uuidv7()"
        },
        "name": {
          "name": "name",
          "type": "varchar(255)",
          "primaryKey": false,
          "notNull": true
        },
        "size": {
          "name": "size",
          "type": "varchar(20)",
          "primaryKey": false,
          "notNull": false
        },
        "file": {
          "name": "file",
          "type": "varchar(255)",
          "primaryKey": false,
          "notNull": false
        }
      },
      "indexes": {},
      "foreignKeys": {},
      "compositePrimaryKeys": {},
      "uniqueConstraints": {},
      "policies": {},
      "checkConstraints": {},
      "isRLSEnabled": false
    },
    "public.features": {
      "name": "features",
      "schema": "",
      "columns": {
        "id": {
          "name": "id",
          "type": "uuid",
          "primaryKey": true,
          "notNull": true,
          "default": "uuidv7()"
        },
        "name": {
          "name": "name",
          "type": "varchar(255)",
          "primaryKey": false,
          "notNull": true
        }
      },
      "indexes": {},
      "foreignKeys": {},
      "compositePrimaryKeys": {},
      "uniqueConstraints": {},
      "policies": {},
      "checkConstraints": {},
      "isRLSEnabled": false
    },
    "public.electronic_types": {
      "name": "electronic_types",
      "schema": "",
      "columns": {
        "id": {
          "name": "id",
          "type": "uuid",
          "primaryKey": true,
          "notNull": true,
          "default": "uuidv7()"
        },
        "name": {
          "name": "name",
          "type": "varchar(255)",
          "primaryKey": false,
          "notNull": true
        }
      },
      "indexes": {},
      "foreignKeys": {},
      "compositePrimaryKeys": {},
      "uniqueConstraints": {},
      "policies": {},
      "checkConstraints": {},
      "isRLSEnabled": false
    },
    "public.products": {
      "name": "products",
      "schema": "",
      "columns": {
        "id": {
          "name": "id",
          "type": "uuid",
          "primaryKey": true,
          "notNull": true,
          "default": "uuidv7()"
        },
        "name": {
          "name": "name",
          "type": "varchar(255)",
          "primaryKey": false,
          "notNull": true
        },
        "slug": {
          "name": "slug",
          "type": "varchar(255)",
          "primaryKey": false,
          "notNull": true
        },
        "thumbnail_url": {
          "name": "thumbnail_url",
          "type": "varchar(255)",
          "primaryKey": false,
          "notNull": true
        },
        "description": {
          "name": "description",
          "type": "text",
          "primaryKey": false,
          "notNull": false
        },
        "stock_qty": {
          "name": "stock_qty",
          "type": "integer",
          "primaryKey": false,
          "notNull": true
        },
        "price": {
          "name": "price",
          "type": "numeric(10, 2)",
          "primaryKey": false,
          "notNull": true
        },
        "specifications": {
          "name": "specifications",
          "type": "jsonb",
          "primaryKey": false,
          "notNull": true
        },
        "discount": {
          "name": "discount",
          "type": "numeric(10, 2)",
          "primaryKey": false,
          "notNull": true
        },
        "is_active": {
          "name": "is_active",
          "type": "boolean",
          "primaryKey": false,
          "notNull": true,
          "default": true
        },
        "is_used": {
          "name": "is_used",
          "type": "boolean",
          "primaryKey": false,
          "notNull": true,
          "default": false
        },
        "brand_id": {
          "name": "brand_id",
          "type": "uuid",
          "primaryKey": false,
          "notNull": false
        },
        "category_id": {
          "name": "category_id",
          "type": "uuid",
          "primaryKey": false,
          "notNull": false
        },
        "datasheet_id": {
          "name": "datasheet_id",
          "type": "uuid",
          "primaryKey": false,
          "notNull": false
        },
        "created_at": {
          "name": "created_at",
          "type": "timestamp with time zone",
          "primaryKey": false,
          "notNull": true,
          "default": "now()"
        },
        "updated_at": {
          "name": "updated_at",
          "type": "timestamp with time zone",
          "primaryKey": false,
          "notNull": false
        }
      },
      "indexes": {},
      "foreignKeys": {
        "products_brand_id_brands_id_fk": {
          "name": "products_brand_id_brands_id_fk",
          "tableFrom": "products",
          "tableTo": "brands",
          "columnsFrom": [
            "brand_id"
          ],
          "columnsTo": [
            "id"
          ],
          "onDelete": "no action",
          "onUpdate": "no action"
        },
        "products_category_id_categories_id_fk": {
          "name": "products_category_id_categories_id_fk",
          "tableFrom": "products",
          "tableTo": "categories",
          "columnsFrom": [
            "category_id"
          ],
          "columnsTo": [
            "id"
          ],
          "onDelete": "no action",
          "onUpdate": "no action"
        },
        "products_datasheet_id_datasheets_id_fk": {
          "name": "products_datasheet_id_datasheets_id_fk",
          "tableFrom": "products",
          "tableTo": "datasheets",
          "columnsFrom": [
            "datasheet_id"
          ],
          "columnsTo": [
            "id"
          ],
          "onDelete": "no action",
          "onUpdate": "no action"
        }
      },
      "compositePrimaryKeys": {},
      "uniqueConstraints": {
        "products_slug_unique": {
          "name": "products_slug_unique",
          "nullsNotDistinct": false,
          "columns": [
            "slug"
          ]
        }
      },
      "policies": {},
      "checkConstraints": {},
      "isRLSEnabled": false
    },
    "public.images": {
      "name": "images",
      "schema": "",
      "columns": {
        "id": {
          "name": "id",
          "type": "uuid",
          "primaryKey": true,
          "notNull": true,
          "default": "uuidv7()"
        },
        "image_url": {
          "name": "image_url",
          "type": "varchar(255)",
          "primaryKey": false,
          "notNull": true
        },
        "product_id": {
          "name": "product_id",
          "type": "uuid",
          "primaryKey": false,
          "notNull": false
        }
      },
      "indexes": {},
      "foreignKeys": {
        "images_product_id_products_id_fk": {
          "name": "images_product_id_products_id_fk",
          "tableFrom": "images",
          "tableTo": "products",
          "columnsFrom": [
            "product_id"
          ],
          "columnsTo": [
            "id"
          ],
          "onDelete": "no action",
          "onUpdate": "no action"
        }
      },
      "compositePrimaryKeys": {},
      "uniqueConstraints": {},
      "policies": {},
      "checkConstraints": {},
      "isRLSEnabled": false
    },
    "public.bulk_price": {
      "name": "bulk_price",
      "schema": "",
      "columns": {
        "id": {
          "name": "id",
          "type": "uuid",
          "primaryKey": true,
          "notNull": true,
          "default": "uuidv7()"
        },
        "qty": {
          "name": "qty",
          "type": "numeric(10, 2)",
          "primaryKey": false,
          "notNull": true
        },
        "price": {
          "name": "price",
          "type": "numeric(10, 2)",
          "primaryKey": false,
          "notNull": true
        },
        "product_id": {
          "name": "product_id",
          "type": "uuid",
          "primaryKey": false,
          "notNull": false
        }
      },
      "indexes": {},
      "foreignKeys": {
        "bulk_price_product_id_products_id_fk": {
          "name": "bulk_price_product_id_products_id_fk",
          "tableFrom": "bulk_price",
          "tableTo": "products",
          "columnsFrom": [
            "product_id"
          ],
          "columnsTo": [
            "id"
          ],
          "onDelete": "no action",
          "onUpdate": "no action"
        }
      },
      "compositePrimaryKeys": {},
      "uniqueConstraints": {},
      "policies": {},
      "checkConstraints": {},
      "isRLSEnabled": false
    },
    "public.electronics": {
      "name": "electronics",
      "schema": "",
      "columns": {
        "id": {
          "name": "id",
          "type": "uuid",
          "primaryKey": true,
          "notNull": true,
          "default": "uuidv7()"
        },
        "sku": {
          "name": "sku",
          "type": "varchar(255)",
          "primaryKey": false,
          "notNull": true
        },
        "package": {
          "name": "package",
          "type": "varchar(255)",
          "primaryKey": false,
          "notNull": true
        },
        "electronic_type_id": {
          "name": "electronic_type_id",
          "type": "uuid",
          "primaryKey": false,
          "notNull": false
        },
        "product_id": {
          "name": "product_id",
          "type": "uuid",
          "primaryKey": false,
          "notNull": false
        }
      },
      "indexes": {},
      "foreignKeys": {
        "electronics_electronic_type_id_electronic_types_id_fk": {
          "name": "electronics_electronic_type_id_electronic_types_id_fk",
          "tableFrom": "electronics",
          "tableTo": "electronic_types",
          "columnsFrom": [
            "electronic_type_id"
          ],
          "columnsTo": [
            "id"
          ],
          "onDelete": "no action",
          "onUpdate": "no action"
        },
        "electronics_product_id_products_id_fk": {
          "name": "electronics_product_id_products_id_fk",
          "tableFrom": "electronics",
          "tableTo": "products",
          "columnsFrom": [
            "product_id"
          ],
          "columnsTo": [
            "id"
          ],
          "onDelete": "no action",
          "onUpdate": "no action"
        }
      },
      "compositePrimaryKeys": {},
      "uniqueConstraints": {
        "electronics_product_id_unique": {
          "name": "electronics_product_id_unique",
          "nullsNotDistinct": false,
          "columns": [
            "product_id"
          ]
        }
      },
      "policies": {},
      "checkConstraints": {},
      "isRLSEnabled": false
    },
    "public.electronics_feature": {
      "name": "electronics_feature",
      "schema": "",
      "columns": {
        "id": {
          "name": "id",
          "type": "uuid",
          "primaryKey": true,
          "notNull": true,
          "default": "uuidv7()"
        },
        "feature_id": {
          "name": "feature_id",
          "type": "uuid",
          "primaryKey": false,
          "notNull": false
        },
        "electronic_id": {
          "name": "electronic_id",
          "type": "uuid",
          "primaryKey": false,
          "notNull": false
        },
        "value": {
          "name": "value",
          "type": "varchar(255)",
          "primaryKey": false,
          "notNull": true
        }
      },
      "indexes": {},
      "foreignKeys": {
        "electronics_feature_feature_id_features_id_fk": {
          "name": "electronics_feature_feature_id_features_id_fk",
          "tableFrom": "electronics_feature",
          "tableTo": "features",
          "columnsFrom": [
            "feature_id"
          ],
          "columnsTo": [
            "id"
          ],
          "onDelete": "no action",
          "onUpdate": "no action"
        },
        "electronics_feature_electronic_id_electronics_id_fk": {
          "name": "electronics_feature_electronic_id_electronics_id_fk",
          "tableFrom": "electronics_feature",
          "tableTo": "electronics",
          "columnsFrom": [
            "electronic_id"
          ],
          "columnsTo": [
            "id"
          ],
          "onDelete": "no action",
          "onUpdate": "no action"
        }
      },
      "compositePrimaryKeys": {},
      "uniqueConstraints": {},
      "policies": {},
      "checkConstraints": {},
      "isRLSEnabled": false
    }
  },
  "enums": {},
  "schemas": {},
  "sequences": {},
  "roles": {},
  "policies": {},
  "views": {},
  "_meta": {
    "columns": {},
    "schemas": {},
    "tables": {}
  }
}